Workbook

Sheet Abrechnung
A1: Spesenaufstellung
A2: Anlage zur Rechnung · Messe London, 06.–07.10.2026 · Sätze siehe Blatt „Saetze 2026“
A4: Rechnung an | B4: CGT UG, Biebricher Allee 36, 65187 Wiesbaden | G4: Gelb = ausfüllen
A5: Von | B5: Sascha Elimar Coldewey, Im Zuckergarten 28, 55129 Mainz | G5: Weiß = rechnet sich
A6: Funktion | B6: Inhaber, CEO | G6: Beträge aus dem
A7: Rechnungsnummer | G7: Kontoauszug belegt.
A8: Reisezweck | B8: Messebesuch London
A9: Reiseziel | B9: London, Vereinigtes Königreich
A10: Reise von (Datum, Uhrzeit) | B10: 06.10.2026, Abflug 10:00
A11: Reise bis (Datum, Uhrzeit) | B11: 07.10.2026, Landung 22:05
A12: Abrechnung erstellt am | B12: 21.10.2026
A13: A · Fahrt mit eigenem Fahrzeug
A14: Datum | B14: Strecke | C14: Fahrzeug | D14: Kilometer | E14: €/km | I14: Betrag
A15: 06.10.2026 | B15: Im Zuckergarten 28 → FRA Terminal 3 und zurück | C15: Pkw, je Kilometer | D15: 70 | E15: =IF($D15="","",IFERROR(INDEX('Saetze 2026'!$C$15:$C$17,MATCH($C15,'Saetze 2026'!$A$15:$A$17,0)),'Saetze 2026'!$C$15)) -> 0.3 | I15: =IF($D15="","",$D15*$E15) -> 21
E16: =IF($D16="","",IFERROR(INDEX('Saetze 2026'!$C$15:$C$17,MATCH($C16,'Saetze 2026'!$A$15:$A$17,0)),'Saetze 2026'!$C$15)) | I16: =IF($D16="","",$D16*$E16)
E17: =IF($D17="","",IFERROR(INDEX('Saetze 2026'!$C$15:$C$17,MATCH($C17,'Saetze 2026'!$A$15:$A$17,0)),'Saetze 2026'!$C$15)) | I17: =IF($D17="","",$D17*$E17)
E18: =IF($D18="","",IFERROR(INDEX('Saetze 2026'!$C$15:$C$17,MATCH($C18,'Saetze 2026'!$A$15:$A$17,0)),'Saetze 2026'!$C$15)) | I18: =IF($D18="","",$D18*$E18)
B19: Summe Fahrt eigenes Fahrzeug | I19: =SUM(I15:I18) -> 21
A21: B · Fahrtkosten und Transport mit Beleg
A22: Datum | B22: Art | C22: Beschreibung | I22: Betrag
A23: 07.10.2026 | B23: Flughafen-Parken | C23: Parkhaus FRA Terminal 3, 06.–07.10. | I23: 86
A24: 07.10.2026 | B24: U-Bahn London | C24: LUL Ticket Machine, 7,00 GBP | I24: 8.26
A25: 07.10.2026 | B25: TfL Nachzahlung | C25: TFL Unpaid Fare, 26,00 GBP — siehe Hinweis | I25: 30.68
A26: 06.10.2026 | B26: Nahverkehr London | C26: About Town Business Services, 3,15 GBP | I26: 3.73
A27: 07.10.2026 | B27: Nahverkehr London | C27: About Town Business Services, 3,15 GBP | I27: 3.72
A28: 07.10.2026 | B28: Nahverkehr London | C28: About Town Business Services, 2,00 GBP | I28: 2.36
B31: Summe Fahrtkosten mit Beleg | I31: =SUM(I23:I30) -> 134.75
A33: C · Verpflegungsmehraufwand (Pauschale, kein Beleg nötig)
A34: Datum | B34: Ort / Land | C34: Abwesenheit | D34: Pauschale | E34: Kürzung | F34: F | G34: M | H34: A | I34: Betrag
A35: 06.10.2026 | B35: London | C35: An-/Abreisetag | D35: =IF($A35="","",IFERROR(INDEX('Saetze 2026'!$C$5:$F$7,MATCH($B35,'Saetze 2026'!$B$5:$B$7,0),MATCH($C35,'Saetze 2026'!$C$4:$F$4,0)),0)) -> 44 | E35: =IF($A35="","",IFERROR(INDEX('Saetze 2026'!$C$5:$C$7,MATCH($B35,'Saetze 2026'!$B$5:$B$7,0)),0)*(IF(LOWER($F35)="x",'Saetze 2026'!$B$10,0)+IF(LOWER($G35)="x",'Saetze 2026'!$B$11,0)+IF(LOWER($H35)="x",'Saetze 2026'!$B$12,0))) -> 0 | I35: =IF($A35="","",MAX(0,$D35-$E35)) -> 44
A36: 07.10.2026 | B36: London | C36: An-/Abreisetag | D36: =IF($A36="","",IFERROR(INDEX('Saetze 2026'!$C$5:$F$7,MATCH($B36,'Saetze 2026'!$B$5:$B$7,0),MATCH($C36,'Saetze 2026'!$C$4:$F$4,0)),0)) -> 44 | E36: =IF($A36="","",IFERROR(INDEX('Saetze 2026'!$C$5:$C$7,MATCH($B36,'Saetze 2026'!$B$5:$B$7,0)),0)*(IF(LOWER($F36)="x",'Saetze 2026'!$B$10,0)+IF(LOWER($G36)="x",'Saetze 2026'!$B$11,0)+IF(LOWER($H36)="x",'Saetze 2026'!$B$12,0))) -> 0 | I36: =IF($A36="","",MAX(0,$D36-$E36)) -> 44
D37: =IF($A37="","",IFERROR(INDEX('Saetze 2026'!$C$5:$F$7,MATCH($B37,'Saetze 2026'!$B$5:$B$7,0),MATCH($C37,'Saetze 2026'!$C$4:$F$4,0)),0)) | E37: =IF($A37="","",IFERROR(INDEX('Saetze 2026'!$C$5:$C$7,MATCH($B37,'Saetze 2026'!$B$5:$B$7,0)),0)*(IF(LOWER($F37)="x",'Saetze 2026'!$B$10,0)+IF(LOWER($G37)="x",'Saetze 2026'!$B$11,0)+IF(LOWER($H37)="x",'Saetze 2026'!$B$12,0))) | I37: =IF($A37="","",MAX(0,$D37-$E37))
D38: =IF($A38="","",IFERROR(INDEX('Saetze 2026'!$C$5:$F$7,MATCH($B38,'Saetze 2026'!$B$5:$B$7,0),MATCH($C38,'Saetze 2026'!$C$4:$F$4,0)),0)) | E38: =IF($A38="","",IFERROR(INDEX('Saetze 2026'!$C$5:$C$7,MATCH($B38,'Saetze 2026'!$B$5:$B$7,0)),0)*(IF(LOWER($F38)="x",'Saetze 2026'!$B$10,0)+IF(LOWER($G38)="x",'Saetze 2026'!$B$11,0)+IF(LOWER($H38)="x",'Saetze 2026'!$B$12,0))) | I38: =IF($A38="","",MAX(0,$D38-$E38))
D39: =IF($A39="","",IFERROR(INDEX('Saetze 2026'!$C$5:$F$7,MATCH($B39,'Saetze 2026'!$B$5:$B$7,0),MATCH($C39,'Saetze 2026'!$C$4:$F$4,0)),0)) | E39: =IF($A39="","",IFERROR(INDEX('Saetze 2026'!$C$5:$C$7,MATCH($B39,'Saetze 2026'!$B$5:$B$7,0)),0)*(IF(LOWER($F39)="x",'Saetze 2026'!$B$10,0)+IF(LOWER($G39)="x",'Saetze 2026'!$B$11,0)+IF(LOWER($H39)="x",'Saetze 2026'!$B$12,0))) | I39: =IF($A39="","",MAX(0,$D39-$E39))
D40: =IF($A40="","",IFERROR(INDEX('Saetze 2026'!$C$5:$F$7,MATCH($B40,'Saetze 2026'!$B$5:$B$7,0),MATCH($C40,'Saetze 2026'!$C$4:$F$4,0)),0)) | E40: =IF($A40="","",IFERROR(INDEX('Saetze 2026'!$C$5:$C$7,MATCH($B40,'Saetze 2026'!$B$5:$B$7,0)),0)*(IF(LOWER($F40)="x",'Saetze 2026'!$B$10,0)+IF(LOWER($G40)="x",'Saetze 2026'!$B$11,0)+IF(LOWER($H40)="x",'Saetze 2026'!$B$12,0))) | I40: =IF($A40="","",MAX(0,$D40-$E40))
B41: Summe Verpflegungsmehraufwand | I41: =SUM(I35:I40) -> 88
A43: D · Übernachtung (mit Beleg, ohne Frühstücksanteil)
A44: Datum | B44: Hotel / Ort | C44: Beleg-Nr. | I44: Betrag
B45: Hotel London, Nacht 06. auf 07.10. — von der Firma direkt gezahlt, keine Auslage von Sascha
B48: Summe Übernachtung | I48: =SUM(I45:I47) -> 0
A50: E · Sonstige Reisenebenkosten
A51: Datum | B51: Art | C51: Beschreibung | I51: Betrag
A52: 06.10.2026 | B52: Einreisegenehmigung | C52: UKVI ETA, Pflicht für UK-Einreise | I52: 24.23
B56: Summe sonstige Nebenkosten | I56: =SUM(I52:I55) -> 24.23
A58: Ergebnis
B59: Summe A bis E | I59: =I19+I31+I41+I48+I56 -> 267.98
B60: abzüglich Vorschuss
B61: abzüglich direkt von der Firma bezahlt
B62: Spesen netto, in die Rechnung zu übernehmen | I62: =I59-N(I60)-N(I61) -> 267.98
A65: _______________________________ | E65: _______________________________
A66: Ort, Datum | E66: Unterschrift
A69: Offene Punkte und bewusst nicht aufgenommene Positionen
A70: OFFEN | B70: Welche Messe? | C70: Im Kopf steht „Messebesuch London“. Den Namen der Messe ergänzen und die Eintrittskarte oder Registrierungsbestätigung beilegen — das ist der Nachweis des betrieblichen Anlasses, nach dem eine Prüfung als Erstes fragt.
A71: — | B71: Flüge | C71: Nicht in dieser Abrechnung: beide Flüge (201,95 €) hat die Coldewey Holding GmbH gezahlt und belastet sie CGT separat weiter. Siehe die zweite Datei, „Weiterbelastung Flüge“.
A72: OFFEN | B72: Umsatzsteuer | C72: Du stellst CGT eine Rechnung, bist also kein Angestellter, sondern Dienstleister. Weiterberechnete Spesen sind dann Teil deines Entgelts und gehören mit 19 % in die Rechnung — auch die Verpflegungspauschale und auch, wenn eine Einzelposition selbst steuerfrei war. Die 267,98 € sind deshalb als Netto zu lesen.
A73: — | B73: Verpflegungspauschale | C73: 88,00 € kannst du als Betriebsausgabe ansetzen, die Pauschalen gelten für Selbstständige genauso. Belege brauchst du dafür nicht, die Abwesenheitszeiten genügen.
A74: — | B74: Hotel | C74: Von der Firma direkt gezahlt, daher nicht in dieser Abrechnung. War Frühstück im Preis, kürzt sich die Verpflegungspauschale um 13,20 € — dann in Block C Zeile 41 ein „x“ in Spalte F setzen.
A75: OFFEN | B75: TfL 30,68 € | C75: „Unpaid Fare“: Fahrpreis-Nachzahlung ist absetzbar, ein Bußgeld nicht. Prüfen.
A76: OFFEN | B76: About Town | C76: 3 Buchungen über zusammen 9,81 € nicht eindeutig zuzuordnen. Prüfen.
A77: — | B77: UPS-Einfuhrabgaben | C77: 11,23 €, Paket zugestellt am 26.08.2026 — sechs Wochen vor dieser Reise und ohne Bezug zu ihr. Gehört nicht in die Reisekostenabrechnung, sondern als eigene Betriebsausgabe gebucht, falls die Sendung betrieblich war. Im privaten Kontoauszug ist die Zahlung nicht zu finden.
A78: — | B78: Essen in London | C78: Pret a Manger, Costa, Nazari Food, WH Smith: zusammen 43,74 €. Wird NICHT zusätzlich erstattet, die Verpflegungspauschale deckt das ab. Die Pauschale von 88 € liegt deutlich darüber.
A79: — | B79: Belegdaten | C79: Die Daten in den Blöcken B und E sind die Kauftage. Im Kontoauszug stehen sie ein bis zwei Tage später, weil der Händler den Kartenumsatz erst dann einreicht. Deshalb sah der Auszug zunächst nach 07.–08.10. aus.
A80: — | B80: Vorsteuer Flüge | C80: Grenzüberschreitende Flüge sind in Deutschland nicht umsatzsteuerpflichtig. Aus den 201,95 € ist keine Vorsteuer zu ziehen.

Sheet Saetze 2026
A1: Pauschalen 2026
A2: Diese Werte steuern die Formeln im Blatt „Abrechnung“. Ändern sich die Sätze, nur hier anfassen.
A4: Ort / Land | B4: Schlüssel | C4: voller Tag (24 h) | D4: An-/Abreisetag | E4: über 8 h | F4: unter 8 h | G4: Übernachtung ohne Beleg
A5: Deutschland (Inland) | B5: Inland | C5: 28 | D5: 14 | E5: 14 | F5: 0 | G5: —
A6: London | B6: London | C6: 66 | D6: 44 | E6: 44 | F6: 0 | G6: 163
A7: Vereinigtes Königreich übrig | B7: Großbritannien | C7: 52 | D7: 35 | E7: 35 | F7: 0 | G7: 99
A9: Kürzung bei gestellter Mahlzeit — Anteil vom vollen Tagessatz des jeweiligen Ortes
A10: Frühstück | B10: 0.2
A11: Mittagessen | B11: 0.4
A12: Abendessen | B12: 0.4
A14: Fahrtkosten eigenes Fahrzeug (Dienstreise)
A15: Pkw, je Kilometer | C15: 0.3
A16: Motorrad / Moped, je Kilometer | C16: 0.2
A17: Fahrrad, je Kilometer | C17: 0.05
A20: Quellen und Vorbehalte
A21: Inland 28 €/14 €: § 9 Abs. 4a EStG, für 2026 unverändert.
A22: London 66 €/44 €, Übernachtung 163 €: BMF-Schreiben vom 05.12.2025 zu Auslandsreisekosten ab 01.01.2026.
A23: Übereinstimmend aus mehreren Sekundärquellen; vor Einreichung gegen die amtliche BMF-Tabelle prüfen.
A24: Kilometersatz Dienstreise Pkw 0,30 €/km: für 2026 unverändert.
A25: Entfernungspauschale ab 2026 einheitlich 0,38 €/km — betrifft diese Abrechnung NICHT.
A26: Übernachtungspauschale ohne Beleg: nur für die steuerfreie Arbeitgeber-Erstattung,
A27: nicht für den Betriebsausgabenabzug. Vor Nutzung mit dem Steuerberater klären.
